cloudnetpy/__init__.py
cloudnetpy/cli.py
cloudnetpy/cloudnetarray.py
cloudnetpy/concat_lib.py
cloudnetpy/constants.py
cloudnetpy/datasource.py
cloudnetpy/exceptions.py
cloudnetpy/metadata.py
cloudnetpy/output.py
cloudnetpy/py.typed
cloudnetpy/utils.py
cloudnetpy/version.py
cloudnetpy/categorize/__init__.py
cloudnetpy/categorize/atmos_utils.py
cloudnetpy/categorize/attenuation.py
cloudnetpy/categorize/categorize.py
cloudnetpy/categorize/classify.py
cloudnetpy/categorize/containers.py
cloudnetpy/categorize/disdrometer.py
cloudnetpy/categorize/droplet.py
cloudnetpy/categorize/falling.py
cloudnetpy/categorize/freezing.py
cloudnetpy/categorize/insects.py
cloudnetpy/categorize/itu.py
cloudnetpy/categorize/lidar.py
cloudnetpy/categorize/melting.py
cloudnetpy/categorize/model.py
cloudnetpy/categorize/mwr.py
cloudnetpy/categorize/radar.py
cloudnetpy/categorize/attenuations/__init__.py
cloudnetpy/categorize/attenuations/gas_attenuation.py
cloudnetpy/categorize/attenuations/liquid_attenuation.py
cloudnetpy/categorize/attenuations/melting_attenuation.py
cloudnetpy/categorize/attenuations/rain_attenuation.py
cloudnetpy/instruments/__init__.py
cloudnetpy/instruments/basta.py
cloudnetpy/instruments/bowtie.py
cloudnetpy/instruments/ceilo.py
cloudnetpy/instruments/ceilometer.py
cloudnetpy/instruments/cl61d.py
cloudnetpy/instruments/cloudnet_instrument.py
cloudnetpy/instruments/copernicus.py
cloudnetpy/instruments/da10.py
cloudnetpy/instruments/fd12p.py
cloudnetpy/instruments/galileo.py
cloudnetpy/instruments/hatpro.py
cloudnetpy/instruments/instruments.py
cloudnetpy/instruments/lufft.py
cloudnetpy/instruments/mira.py
cloudnetpy/instruments/mrr.py
cloudnetpy/instruments/nc_lidar.py
cloudnetpy/instruments/nc_radar.py
cloudnetpy/instruments/pollyxt.py
cloudnetpy/instruments/radiometrics.py
cloudnetpy/instruments/rain_e_h3.py
cloudnetpy/instruments/rpg.py
cloudnetpy/instruments/rpg_reader.py
cloudnetpy/instruments/toa5.py
cloudnetpy/instruments/vaisala.py
cloudnetpy-1.87.3.dist-info/licenses/LICENSE
cloudnetpy-1.87.3.dist-info/METADATA
cloudnetpy-1.87.3.dist-info/WHEEL
cloudnetpy-1.87.3.dist-info/entry_points.txt
cloudnetpy-1.87.3.dist-info/top_level.txt
cloudnetpy-1.87.3.dist-info/RECORD
