Metadata-Version: 2.4
Name: cloudnetpy
Version: 1.87.3
Summary: Python package for Cloudnet processing
Author: Simo Tukiainen
License: MIT License
Project-URL: Homepage, https://github.com/actris-cloudnet/cloudnetpy
Project-URL: Documentation, https://actris-cloudnet.github.io/cloudnetpy/
Project-URL: Repository, https://github.com/actris-cloudnet/cloudnetpy
Project-URL: Changelog, https://github.com/actris-cloudnet/cloudnetpy/blob/main/CHANGELOG.md
Classifier: Development Status :: 5 - Production/Stable
Classifier: Intended Audience :: Science/Research
Classifier: License :: OSI Approved :: MIT License
Classifier: Operating System :: OS Independent
Classifier: Programming Language :: Python :: 3
Classifier: Topic :: Scientific/Engineering :: Atmospheric Science
Requires-Python: >=3.10
License-File: LICENSE
Requires-Dist: ceilopyter>=0.2.0
Requires-Dist: cloudnet-api-client
Requires-Dist: doppy>=0.5.0
Requires-Dist: matplotlib
Requires-Dist: mwrpy>=1.3.5
Requires-Dist: netCDF4
Requires-Dist: requests
Requires-Dist: rpgpy>=0.14.5
Requires-Dist: scipy
Requires-Dist: typing-extensions
Provides-Extra: test
Requires-Dist: cloudnetpy_qc; extra == "test"
Requires-Dist: mypy; extra == "test"
Requires-Dist: pytest; extra == "test"
Requires-Dist: pytest-flakefinder; extra == "test"
Requires-Dist: ruff; extra == "test"
Requires-Dist: types-requests; extra == "test"
Provides-Extra: dev
Requires-Dist: pre-commit; extra == "dev"
Requires-Dist: release-version; extra == "dev"
Provides-Extra: extras
Requires-Dist: voodoonet>=0.1.7; extra == "extras"
Dynamic: license-file
